pipe_mips32.v
module pipe_MIPS32 (clk1, clk2);

  input clk1, clk2;   // Two-phase clock

  // Pipeline registers
  reg [31:0] PC, IF_ID_IR, IF_ID_NPC;
  reg [31:0] ID_EX_IR, ID_EX_NPC, ID_EX_A, ID_EX_B, ID_EX_Imm;
  reg [2:0]  ID_EX_type, EX_MEM_type, MEM_WB_type;
  reg [31:0] EX_MEM_IR, EX_MEM_ALUOut, EX_MEM_B;
  reg        EX_MEM_cond;
  reg [31:0] MEM_WB_IR, MEM_WB_ALUOut, MEM_WB_LMD;

  // Register bank (32 x 32) and memory (1024 x 32)
  reg [31:0] Reg [0:31];
  reg [31:0] Mem [0:1023];

  // OPCODE definitions
  parameter ADD   = 6'b000000,
            SUB   = 6'b000001,
            AND   = 6'b000010,
            OR    = 6'b000011,
            SLT   = 6'b000100,
            MUL   = 6'b000101,
            HLT   = 6'b111111,
            LW    = 6'b001000,
            SW    = 6'b001001,
            ADDI  = 6'b001010,
            SUBI  = 6'b001011,
            SLTI  = 6'b001100,
            BNEQZ = 6'b001101,
            BEQZ  = 6'b001110;

  // Instruction type definitions
  parameter RR_ALU = 3'b000,
            RM_ALU = 3'b001,
            LOAD   = 3'b010,
            STORE  = 3'b011,
            BRANCH = 3'b100,
            HALT   = 3'b101;

  reg HALTED;        // Set after HLT instruction is completed (in WB stage)
  reg TAKEN_BRANCH;  // Required to disable instructions after branch

  //===========================================
  // IF Stage
  //===========================================
  always @(posedge clk1)
  begin
    if (HALTED == 0)
    begin
      // Check for taken branch
      if (((EX_MEM_IR[31:26] == BEQZ) && (EX_MEM_cond == 1)) ||
          ((EX_MEM_IR[31:26] == BNEQZ) && (EX_MEM_cond == 0)))
      begin
        IF_ID_IR     <= #2 Mem[EX_MEM_ALUOut];
        IF_ID_NPC    <= #2 EX_MEM_ALUOut + 1;
        PC           <= #2 EX_MEM_ALUOut + 1;
        TAKEN_BRANCH <= #2 1'b1;
      end
      else
      begin
        IF_ID_IR  <= #2 Mem[PC];
        IF_ID_NPC <= #2 (PC + 1);
        PC        <= #2 (PC + 1);
      end
    end
  end

  //===========================================
  // ID Stage
  //===========================================
  always @(posedge clk2)
  begin
    if (HALTED == 0)
    begin
      // Read registers (rs, rt)
      if (IF_ID_IR[25:21] == 5'b00000)
        ID_EX_A <= 0;
      else
        ID_EX_A <= #2 Reg[IF_ID_IR[25:21]];

      if (IF_ID_IR[20:16] == 5'b00000)
        ID_EX_B <= 0;
      else
        ID_EX_B <= #2 Reg[IF_ID_IR[20:16]];

      // Pass along PC, IR
      ID_EX_NPC <= #2 IF_ID_NPC;
      ID_EX_IR  <= #2 IF_ID_IR;
      ID_EX_Imm <= #2 {{16{IF_ID_IR[15]}}, IF_ID_IR[15:0]};

      // Determine instruction type
      case (IF_ID_IR[31:26])
        ADD, SUB, AND, OR, SLT, MUL: ID_EX_type <= #2 RR_ALU;
        ADDI, SUBI, SLTI:           ID_EX_type <= #2 RM_ALU;
        LW:                         ID_EX_type <= #2 LOAD;
        SW:                         ID_EX_type <= #2 STORE;
        BNEQZ, BEQZ:               ID_EX_type <= #2 BRANCH;
        HLT:                        ID_EX_type <= #2 HALT;
        default:                    ID_EX_type <= #2 HALT;
      endcase
    end
  end

  //===========================================
  // EX Stage
  //===========================================
  always @(posedge clk1)
  begin
    if (HALTED == 0)
    begin
      EX_MEM_type  <= #2 ID_EX_type;
      EX_MEM_IR    <= #2 ID_EX_IR;
      TAKEN_BRANCH <= #2 0;

      case (ID_EX_type)
        RR_ALU:
        begin
          case (ID_EX_IR[31:26])
            ADD: EX_MEM_ALUOut <= #2 (ID_EX_A + ID_EX_B);
            SUB: EX_MEM_ALUOut <= #2 (ID_EX_A - ID_EX_B);
            AND: EX_MEM_ALUOut <= #2 (ID_EX_A & ID_EX_B);
            OR:  EX_MEM_ALUOut <= #2 (ID_EX_A | ID_EX_B);
            SLT: EX_MEM_ALUOut <= #2 ((ID_EX_A < ID_EX_B) ? 1 : 0);
            MUL: EX_MEM_ALUOut <= #2 (ID_EX_A * ID_EX_B);
            default: EX_MEM_ALUOut <= #2 32'hxxxxxxxx;
          endcase
        end

        RM_ALU:
        begin
          case (ID_EX_IR[31:26])
            ADDI: EX_MEM_ALUOut <= #2 (ID_EX_A + ID_EX_Imm);
            SUBI: EX_MEM_ALUOut <= #2 (ID_EX_A - ID_EX_Imm);
            SLTI: EX_MEM_ALUOut <= #2 ((ID_EX_A < ID_EX_Imm) ? 1 : 0);
            default: EX_MEM_ALUOut <= #2 32'hxxxxxxxx;
          endcase
        end

        LOAD, STORE:
        begin
          EX_MEM_ALUOut <= #2 (ID_EX_A + ID_EX_Imm);
          EX_MEM_B      <= #2 ID_EX_B;  // For STORE
        end

        BRANCH:
        begin
          EX_MEM_ALUOut <= #2 (ID_EX_NPC + ID_EX_Imm);
          EX_MEM_cond   <= #2 (ID_EX_A == 0);
        end
      endcase
    end
  end

  //===========================================
  // MEM Stage
  //===========================================
  always @(posedge clk2)
  begin
    if (HALTED == 0)
    begin
      MEM_WB_type <= #2 EX_MEM_type;
      MEM_WB_IR   <= #2 EX_MEM_IR;

      case (EX_MEM_type)
        RR_ALU, RM_ALU:
          MEM_WB_ALUOut <= #2 EX_MEM_ALUOut;

        LOAD:
          MEM_WB_LMD <= #2 Mem[EX_MEM_ALUOut];

        STORE:
          // Only store if branch not taken
          if (TAKEN_BRANCH == 0)
            Mem[EX_MEM_ALUOut] <= #2 EX_MEM_B;

        BRANCH: 
          // No direct MEM result, but we have updated PC in IF stage
          ;

        HALT:
          // No memory action for HLT
          ;
      endcase
    end
  end

  //===========================================
  // WB Stage
  //===========================================
  always @(posedge clk1)
  begin
    // Disable write if branch was taken
    if (TAKEN_BRANCH == 0)
    begin
      case (MEM_WB_type)
        RR_ALU:
          // rd
          Reg[MEM_WB_IR[15:11]] <= #2 MEM_WB_ALUOut;

        RM_ALU:
          // rt
          Reg[MEM_WB_IR[20:16]] <= #2 MEM_WB_ALUOut;

        LOAD:
          // rt
          Reg[MEM_WB_IR[20:16]] <= #2 MEM_WB_LMD;

        HALT:
          HALTED <= #2 1'b1;
      endcase
    end
  end

endmodule

testbench1.v
module test1_MIPS32;
    reg clk1, clk2;
    integer k;

    pipe_MIPS32 DUT(clk1, clk2);

    // Clock generation
    initial begin
        clk1 = 0; clk2 = 0;
        repeat(50) begin // Extended for full pipeline completion
            #5 clk1 = 1; #5 clk1 = 0;
            #5 clk2 = 1; #5 clk2 = 0;
        end
    end

    // Instruction memory and reg file init
    initial begin
        for (k = 0; k <= 31; k = k + 1)
            DUT.Reg[k] = k;

        DUT.Mem[0] = 32'h2801000a; // ADDI R1, R0, 10
        DUT.Mem[1] = 32'h28020014; // ADDI R2, R0, 20
        DUT.Mem[2] = 32'h28030019; // ADDI R3, R0, 25
        DUT.Mem[3] = 32'h0ce77800; // OR R7,R7,R7 (dummy)
        DUT.Mem[4] = 32'h0ce77800; // dummy
        DUT.Mem[5] = 32'h00222000; // ADD R4 = R1 + R2
        DUT.Mem[6] = 32'h0ce77800; // dummy
        DUT.Mem[7] = 32'h00832800; // ADD R5 = R4 + R3
        DUT.Mem[8] = 32'hfc000000; // HLT

        DUT.HALTED = 0;
        DUT.PC = 0;
        DUT.TAKEN_BRANCH = 0;

        #580 // Wait for all instructions to complete
        for (k = 0; k < 6; k = k + 1)
            $display("R%1d = %2d", k, DUT.Reg[k]);
    end

    // Dump waveform
    initial begin
        $dumpfile("DUT.vcd");
        $dumpvars(1, DUT); // dump internals
        #600 $finish;
    end
endmodule

DUT.vcd
$date
	Sun Jul 27 23:24:35 2025
$end
$version
	Icarus Verilog
$end
$timescale
	1s
$end
$scope module test1_MIPS32 $end
$scope module DUT $end
$var wire 1 ! clk1 $end
$var wire 1 " clk2 $end
$var parameter 6 # ADD $end
$var parameter 6 $ ADDI $end
$var parameter 6 % AND $end
$var parameter 6 & BEQZ $end
$var parameter 6 ' BNEQZ $end
$var parameter 3 ( BRANCH $end
$var parameter 3 ) HALT $end
$var parameter 6 * HLT $end
$var parameter 3 + LOAD $end
$var parameter 6 , LW $end
$var parameter 6 - MUL $end
$var parameter 6 . OR $end
$var parameter 3 / RM_ALU $end
$var parameter 3 0 RR_ALU $end
$var parameter 6 1 SLT $end
$var parameter 6 2 SLTI $end
$var parameter 3 3 STORE $end
$var parameter 6 4 SUB $end
$var parameter 6 5 SUBI $end
$var parameter 6 6 SW $end
$var reg 32 7 EX_MEM_ALUOut [31:0] $end
$var reg 32 8 EX_MEM_B [31:0] $end
$var reg 32 9 EX_MEM_IR [31:0] $end
$var reg 1 : EX_MEM_cond $end
$var reg 3 ; EX_MEM_type [2:0] $end
$var reg 1 < HALTED $end
$var reg 32 = ID_EX_A [31:0] $end
$var reg 32 > ID_EX_B [31:0] $end
$var reg 32 ? ID_EX_IR [31:0] $end
$var reg 32 @ ID_EX_Imm [31:0] $end
$var reg 32 A ID_EX_NPC [31:0] $end
$var reg 3 B ID_EX_type [2:0] $end
$var reg 32 C IF_ID_IR [31:0] $end
$var reg 32 D IF_ID_NPC [31:0] $end
$var reg 32 E MEM_WB_ALUOut [31:0] $end
$var reg 32 F MEM_WB_IR [31:0] $end
$var reg 32 G MEM_WB_LMD [31:0] $end
$var reg 3 H MEM_WB_type [2:0] $end
$var reg 32 I PC [31:0] $end
$var reg 1 J TAKEN_BRANCH $end
$upscope $end
$upscope $end
$enddefinitions $end
$comment Show the parameter values. $end
$dumpall
b1001 6
b1011 5
b1 4
b11 3
b1100 2
b100 1
b0 0
b1 /
b11 .
b101 -
b1000 ,
b10 +
b111111 *
b101 )
b100 (
b1101 '
b1110 &
b10 %
b1010 $
b0 #
$end
#0
$dumpvars
0J
b0 I
bx H
bx G
bx F
bx E
bx D
bx C
bx B
bx A
bx @
bx ?
bx >
bx =
0<
bx ;
x:
bx 9
bx 8
bx 7
0"
0!
$end
#5
1!
#7
b1 I
b1 D
b101000000000010000000000001010 C
#10
0!
#15
b0 =
1"
#17
b1 B
b1010 @
b101000000000010000000000001010 ?
b1 A
b1 >
#20
0"
#25
1!
#27
b1010 7
b101000000000010000000000001010 9
b1 ;
b10 I
b10 D
b101000000000100000000000010100 C
#30
0!
#35
1"
#37
b1010 E
b101000000000010000000000001010 F
b1 H
b10100 @
b101000000000100000000000010100 ?
b10 A
b10 >
#40
0"
#45
1!
#47
b11 I
b11 D
b101000000000110000000000011001 C
b10100 7
b101000000000100000000000010100 9
#50
0!
#55
1"
#57
b11001 @
b101000000000110000000000011001 ?
b11 A
b11 >
b10100 E
b101000000000100000000000010100 F
#60
0"
#65
1!
#67
b11001 7
b101000000000110000000000011001 9
b100 I
b100 D
b1100111001110111100000000000 C
#70
0!
#75
1"
#77
b11001 E
b101000000000110000000000011001 F
b0 B
b111100000000000 @
b1100111001110111100000000000 ?
b100 A
b111 >
b111 =
#80
0"
#85
1!
#87
b101 I
b101 D
b111 7
b1100111001110111100000000000 9
b0 ;
#90
0!
#95
1"
#97
b101 A
b111 E
b1100111001110111100000000000 F
b0 H
#100
0"
#105
1!
#107
b110 I
b110 D
b1000100010000000000000 C
#110
0!
#115
1"
#117
b10000000000000 @
b1000100010000000000000 ?
b110 A
b10100 >
b1010 =
#120
0"
#125
1!
#127
b111 I
b111 D
b1100111001110111100000000000 C
b11110 7
b1000100010000000000000 9
#130
0!
#135
1"
#137
b111100000000000 @
b1100111001110111100000000000 ?
b111 A
b111 >
b111 =
b11110 E
b1000100010000000000000 F
#140
0"
#145
1!
#147
b111 7
b1100111001110111100000000000 9
b1000 I
b1000 D
b100000110010100000000000 C
#150
0!
#155
1"
#157
b111 E
b1100111001110111100000000000 F
b10100000000000 @
b100000110010100000000000 ?
b1000 A
b11001 >
b11110 =
#160
0"
#165
1!
#167
b1001 I
b1001 D
b11111100000000000000000000000000 C
b110111 7
b100000110010100000000000 9
#170
0!
#175
b0 >
b0 =
1"
#177
b101 B
b0 @
b11111100000000000000000000000000 ?
b1001 A
b110111 E
b100000110010100000000000 F
#180
0"
#185
1!
#187
b11111100000000000000000000000000 9
b101 ;
b1010 I
b1010 D
bx C
#190
0!
#195
1"
#197
b11111100000000000000000000000000 F
b101 H
bx @
bx ?
b1010 A
bx >
bx =
#200
0"
#205
1!
#207
b1011 I
b1011 D
bx 9
1<
