pipe_mips32.v
module pipe_MIPS32 (clk1, clk2);

  input clk1, clk2;   // Two-phase clock

  // Pipeline registers
  reg [31:0] PC, IF_ID_IR, IF_ID_NPC;
  reg [31:0] ID_EX_IR, ID_EX_NPC, ID_EX_A, ID_EX_B, ID_EX_Imm;
  reg [2:0]  ID_EX_type, EX_MEM_type, MEM_WB_type;
  reg [31:0] EX_MEM_IR, EX_MEM_ALUOut, EX_MEM_B;
  reg        EX_MEM_cond;
  reg [31:0] MEM_WB_IR, MEM_WB_ALUOut, MEM_WB_LMD;

  // Register bank (32 x 32) and memory (1024 x 32)
  reg [31:0] Reg [0:31];
  reg [31:0] Mem [0:1023];

  // OPCODE definitions
  parameter ADD   = 6'b000000,
            SUB   = 6'b000001,
            AND   = 6'b000010,
            OR    = 6'b000011,
            SLT   = 6'b000100,
            MUL   = 6'b000101,
            HLT   = 6'b111111,
            LW    = 6'b001000,
            SW    = 6'b001001,
            ADDI  = 6'b001010,
            SUBI  = 6'b001011,
            SLTI  = 6'b001100,
            BNEQZ = 6'b001101,
            BEQZ  = 6'b001110;

  // Instruction type definitions
  parameter RR_ALU = 3'b000,
            RM_ALU = 3'b001,
            LOAD   = 3'b010,
            STORE  = 3'b011,
            BRANCH = 3'b100,
            HALT   = 3'b101;

  reg HALTED;        // Set after HLT instruction is completed (in WB stage)
  reg TAKEN_BRANCH;  // Required to disable instructions after branch

  //===========================================
  // IF Stage
  //===========================================
  always @(posedge clk1)
  begin
    if (HALTED == 0)
    begin
      // Check for taken branch
      if (((EX_MEM_IR[31:26] == BEQZ) && (EX_MEM_cond == 1)) ||
          ((EX_MEM_IR[31:26] == BNEQZ) && (EX_MEM_cond == 0)))
      begin
        IF_ID_IR     <= #2 Mem[EX_MEM_ALUOut];
        IF_ID_NPC    <= #2 EX_MEM_ALUOut + 1;
        PC           <= #2 EX_MEM_ALUOut + 1;
        TAKEN_BRANCH <= #2 1'b1;
      end
      else
      begin
        IF_ID_IR  <= #2 Mem[PC];
        IF_ID_NPC <= #2 (PC + 1);
        PC        <= #2 (PC + 1);
      end
    end
  end

  //===========================================
  // ID Stage
  //===========================================
  always @(posedge clk2)
  begin
    if (HALTED == 0)
    begin
      // Read registers (rs, rt)
      if (IF_ID_IR[25:21] == 5'b00000)
        ID_EX_A <= 0;
      else
        ID_EX_A <= #2 Reg[IF_ID_IR[25:21]];

      if (IF_ID_IR[20:16] == 5'b00000)
        ID_EX_B <= 0;
      else
        ID_EX_B <= #2 Reg[IF_ID_IR[20:16]];

      // Pass along PC, IR
      ID_EX_NPC <= #2 IF_ID_NPC;
      ID_EX_IR  <= #2 IF_ID_IR;
      ID_EX_Imm <= #2 {{16{IF_ID_IR[15]}}, IF_ID_IR[15:0]};

      // Determine instruction type
      case (IF_ID_IR[31:26])
        ADD, SUB, AND, OR, SLT, MUL: ID_EX_type <= #2 RR_ALU;
        ADDI, SUBI, SLTI:           ID_EX_type <= #2 RM_ALU;
        LW:                         ID_EX_type <= #2 LOAD;
        SW:                         ID_EX_type <= #2 STORE;
        BNEQZ, BEQZ:               ID_EX_type <= #2 BRANCH;
        HLT:                        ID_EX_type <= #2 HALT;
        default:                    ID_EX_type <= #2 HALT;
      endcase
    end
  end

  //===========================================
  // EX Stage
  //===========================================
  always @(posedge clk1)
  begin
    if (HALTED == 0)
    begin
      EX_MEM_type  <= #2 ID_EX_type;
      EX_MEM_IR    <= #2 ID_EX_IR;
      TAKEN_BRANCH <= #2 0;

      case (ID_EX_type)
        RR_ALU:
        begin
          case (ID_EX_IR[31:26])
            ADD: EX_MEM_ALUOut <= #2 (ID_EX_A + ID_EX_B);
            SUB: EX_MEM_ALUOut <= #2 (ID_EX_A - ID_EX_B);
            AND: EX_MEM_ALUOut <= #2 (ID_EX_A & ID_EX_B);
            OR:  EX_MEM_ALUOut <= #2 (ID_EX_A | ID_EX_B);
            SLT: EX_MEM_ALUOut <= #2 ((ID_EX_A < ID_EX_B) ? 1 : 0);
            MUL: EX_MEM_ALUOut <= #2 (ID_EX_A * ID_EX_B);
            default: EX_MEM_ALUOut <= #2 32'hxxxxxxxx;
          endcase
        end

        RM_ALU:
        begin
          case (ID_EX_IR[31:26])
            ADDI: EX_MEM_ALUOut <= #2 (ID_EX_A + ID_EX_Imm);
            SUBI: EX_MEM_ALUOut <= #2 (ID_EX_A - ID_EX_Imm);
            SLTI: EX_MEM_ALUOut <= #2 ((ID_EX_A < ID_EX_Imm) ? 1 : 0);
            default: EX_MEM_ALUOut <= #2 32'hxxxxxxxx;
          endcase
        end

        LOAD, STORE:
        begin
          EX_MEM_ALUOut <= #2 (ID_EX_A + ID_EX_Imm);
          EX_MEM_B      <= #2 ID_EX_B;  // For STORE
        end

        BRANCH:
        begin
          EX_MEM_ALUOut <= #2 (ID_EX_NPC + ID_EX_Imm);
          EX_MEM_cond   <= #2 (ID_EX_A == 0);
        end
      endcase
    end
  end

  //===========================================
  // MEM Stage
  //===========================================
  always @(posedge clk2)
  begin
    if (HALTED == 0)
    begin
      MEM_WB_type <= #2 EX_MEM_type;
      MEM_WB_IR   <= #2 EX_MEM_IR;

      case (EX_MEM_type)
        RR_ALU, RM_ALU:
          MEM_WB_ALUOut <= #2 EX_MEM_ALUOut;

        LOAD:
          MEM_WB_LMD <= #2 Mem[EX_MEM_ALUOut];

        STORE:
          // Only store if branch not taken
          if (TAKEN_BRANCH == 0)
            Mem[EX_MEM_ALUOut] <= #2 EX_MEM_B;

        BRANCH: 
          // No direct MEM result, but we have updated PC in IF stage
          ;

        HALT:
          // No memory action for HLT
          ;
      endcase
    end
  end

  //===========================================
  // WB Stage
  //===========================================
  always @(posedge clk1)
  begin
    // Disable write if branch was taken
    if (TAKEN_BRANCH == 0)
    begin
      case (MEM_WB_type)
        RR_ALU:
          // rd
          Reg[MEM_WB_IR[15:11]] <= #2 MEM_WB_ALUOut;

        RM_ALU:
          // rt
          Reg[MEM_WB_IR[20:16]] <= #2 MEM_WB_ALUOut;

        LOAD:
          // rt
          Reg[MEM_WB_IR[20:16]] <= #2 MEM_WB_LMD;

        HALT:
          HALTED <= #2 1'b1;
      endcase
    end
  end

endmodule

testbench2.v
module test_mips32;
  reg clk1, clk2;
  integer k;
  
  // Instantiate the pipelined MIPS module
  pipe_MIPS32 mips (clk1, clk2);
  
  // Clock Generation: Two-phase clock generation using repeat loop
  initial begin
    clk1 = 0;
    clk2 = 0;
    repeat (50) begin
      #5 clk1 = 1;  #5 clk1 = 0;
      #5 clk2 = 1;  #5 clk2 = 0;
    end
  end
  
  // Initialize Registers and Memory
  initial begin
    // Initialize register file: R0-R30 with values 0 to 30
    for (k = 0; k < 31; k = k + 1)
      mips.Reg[k] = k;
      
    // Load instructions and data into memory
    mips.Mem[0] = 32'h28010078;  // ADDI  R1, R0, 120
    mips.Mem[1] = 32'h0c631800;   // OR    R3, R3, R3 -- dummy instruction
    mips.Mem[2] = 32'h20220000;   // LW    R2, 0(R1)
    mips.Mem[3] = 32'h0c631800;   // OR    R3, R3, R3 -- dummy instruction
    mips.Mem[4] = 32'h2842002d;   // ADDI  R2, R2, 45
    mips.Mem[5] = 32'h0c631800;   // OR    R3, R3, R3 -- dummy instruction
    mips.Mem[6] = 32'h24220001;   // SW    R2, 1(R1)
    mips.Mem[7] = 32'hfc000000;   // HLT
    mips.Mem[120] = 85;          // Data value at memory address 120
    
    // Initialize PC and control signals
    mips.PC = 0;
    mips.HALTED = 0;
    mips.TAKEN_BRANCH = 0;
    
    #500;
    $display("Mem[120]: %4d \nMem[121]: %4d", mips.Mem[120], mips.Mem[121]);
  end
  
  // Dump waveforms and finish simulation
  initial begin
    $dumpfile("mips.vcd");
    $dumpvars(1, mips);
    #600 $finish;
  end
  
endmodule

mips.vcd
$date
	Sun Jul 27 23:32:59 2025
$end
$version
	Icarus Verilog
$end
$timescale
	1s
$end
$scope module test_mips32 $end
$scope module mips $end
$var wire 1 ! clk1 $end
$var wire 1 " clk2 $end
$var parameter 6 # ADD $end
$var parameter 6 $ ADDI $end
$var parameter 6 % AND $end
$var parameter 6 & BEQZ $end
$var parameter 6 ' BNEQZ $end
$var parameter 3 ( BRANCH $end
$var parameter 3 ) HALT $end
$var parameter 6 * HLT $end
$var parameter 3 + LOAD $end
$var parameter 6 , LW $end
$var parameter 6 - MUL $end
$var parameter 6 . OR $end
$var parameter 3 / RM_ALU $end
$var parameter 3 0 RR_ALU $end
$var parameter 6 1 SLT $end
$var parameter 6 2 SLTI $end
$var parameter 3 3 STORE $end
$var parameter 6 4 SUB $end
$var parameter 6 5 SUBI $end
$var parameter 6 6 SW $end
$var reg 32 7 EX_MEM_ALUOut [31:0] $end
$var reg 32 8 EX_MEM_B [31:0] $end
$var reg 32 9 EX_MEM_IR [31:0] $end
$var reg 1 : EX_MEM_cond $end
$var reg 3 ; EX_MEM_type [2:0] $end
$var reg 1 < HALTED $end
$var reg 32 = ID_EX_A [31:0] $end
$var reg 32 > ID_EX_B [31:0] $end
$var reg 32 ? ID_EX_IR [31:0] $end
$var reg 32 @ ID_EX_Imm [31:0] $end
$var reg 32 A ID_EX_NPC [31:0] $end
$var reg 3 B ID_EX_type [2:0] $end
$var reg 32 C IF_ID_IR [31:0] $end
$var reg 32 D IF_ID_NPC [31:0] $end
$var reg 32 E MEM_WB_ALUOut [31:0] $end
$var reg 32 F MEM_WB_IR [31:0] $end
$var reg 32 G MEM_WB_LMD [31:0] $end
$var reg 3 H MEM_WB_type [2:0] $end
$var reg 32 I PC [31:0] $end
$var reg 1 J TAKEN_BRANCH $end
$upscope $end
$upscope $end
$enddefinitions $end
$comment Show the parameter values. $end
$dumpall
b1001 6
b1011 5
b1 4
b11 3
b1100 2
b100 1
b0 0
b1 /
b11 .
b101 -
b1000 ,
b10 +
b111111 *
b101 )
b100 (
b1101 '
b1110 &
b10 %
b1010 $
b0 #
$end
#0
$dumpvars
0J
b0 I
bx H
bx G
bx F
bx E
bx D
bx C
bx B
bx A
bx @
bx ?
bx >
bx =
0<
bx ;
x:
bx 9
bx 8
bx 7
0"
0!
$end
#5
1!
#7
b1 I
b1 D
b101000000010100000000011001000 C
#10
0!
#15
b0 =
1"
#17
b1 B
b11001000 @
b101000000010100000000011001000 ?
b1 A
b1010 >
#20
0"
#25
1!
#27
b11001000 7
b101000000010100000000011001000 9
b1 ;
b10 I
b10 D
b101000000000100000000000000001 C
#30
0!
#35
1"
#37
b11001000 E
b101000000010100000000011001000 F
b1 H
b1 @
b101000000000100000000000000001 ?
b10 A
b10 >
#40
0"
#45
1!
#47
b11 I
b11 D
b1110100101001010000000000000 C
b1 7
b101000000000100000000000000001 9
#50
0!
#55
1"
#57
b0 B
b11111111111111111010000000000000 @
b1110100101001010000000000000 ?
b11 A
b10100 >
b10100 =
b1 E
b101000000000100000000000000001 F
#60
0"
#65
1!
#67
b10100 7
b1110100101001010000000000000 9
b0 ;
b100 I
b100 D
b100001010000110000000000000000 C
#70
0!
#75
1"
#77
b10100 E
b1110100101001010000000000000 F
b0 H
b10 B
b0 @
b100001010000110000000000000000 ?
b100 A
b11 >
b11001000 =
#80
0"
#85
1!
#87
b101 I
b101 D
b1110100101001010000000000000 C
b11 8
b11001000 7
b100001010000110000000000000000 9
b10 ;
#90
0!
#95
1"
#97
b0 B
b11111111111111111010000000000000 @
b1110100101001010000000000000 ?
b101 A
b10100 >
b10100 =
b111 G
b100001010000110000000000000000 F
b10 H
#100
0"
#105
1!
#107
b10100 7
b1110100101001010000000000000 9
b0 ;
b110 I
b110 D
b10100010000110001000000000000 C
#110
0!
#115
1"
#117
b1110100101001010000000000000 F
b0 H
b1000000000000 @
b10100010000110001000000000000 ?
b110 A
b111 >
b1 =
#120
0"
#125
1!
#127
b111 I
b111 D
b101100011000110000000000000001 C
b111 7
b10100010000110001000000000000 9
#130
0!
#135
1"
#137
b1 B
b1 @
b101100011000110000000000000001 ?
b111 A
b111 =
b111 E
b10100010000110001000000000000 F
#140
0"
#145
1!
#147
b110 7
b101100011000110000000000000001 9
b1 ;
b1000 I
b1000 D
b1110100101001010000000000000 C
#150
0!
#155
1"
#157
b110 E
b101100011000110000000000000001 F
b1 H
b0 B
b11111111111111111010000000000000 @
b1110100101001010000000000000 ?
b1000 A
b10100 >
b10100 =
#160
0"
#165
1!
#167
b1001 I
b1001 D
b110100011000001111111111111100 C
b10100 7
b1110100101001010000000000000 9
b0 ;
#170
0!
#175
b0 >
1"
#177
b100 B
b11111111111111111111111111111100 @
b110100011000001111111111111100 ?
b1001 A
b110 =
b10100 E
b1110100101001010000000000000 F
b0 H
#180
0"
#185
1!
#187
0:
b101 7
b110100011000001111111111111100 9
b100 ;
b1010 I
b1010 D
b100101010000101111111111111110 C
#190
0!
#195
1"
#197
b110100011000001111111111111100 F
b100 H
b11 B
b11111111111111111111111111111110 @
b100101010000101111111111111110 ?
b1010 A
b111 >
b11001000 =
#200
0"
#205
1!
#207
1J
b110 I
b110 D
b10100010000110001000000000000 C
b111 8
b11000110 7
b100101010000101111111111111110 9
b11 ;
#210
0!
#215
1"
#217
b0 B
b1000000000000 @
b10100010000110001000000000000 ?
b110 A
b110 >
b111 =
b100101010000101111111111111110 F
b11 H
#220
0"
#225
1!
#227
b101010 7
0J
b10100010000110001000000000000 9
b0 ;
b111 I
b111 D
b101100011000110000000000000001 C
#230
0!
#235
1"
#237
b101010 E
b10100010000110001000000000000 F
b0 H
b1 B
b1 @
b101100011000110000000000000001 ?
b111 A
b110 =
#240
0"
#245
1!
#247
b1000 I
b1000 D
b1110100101001010000000000000 C
b101 7
b101100011000110000000000000001 9
b1 ;
#250
0!
#255
1"
#257
b0 B
b11111111111111111010000000000000 @
b1110100101001010000000000000 ?
b1000 A
b10100 >
b10100 =
b101 E
b101100011000110000000000000001 F
b1 H
#260
0"
#265
1!
#267
b10100 7
b1110100101001010000000000000 9
b0 ;
b1001 I
b1001 D
b110100011000001111111111111100 C
#270
0!
#275
b0 >
1"
#277
b10100 E
b1110100101001010000000000000 F
b0 H
b100 B
b11111111111111111111111111111100 @
b110100011000001111111111111100 ?
b1001 A
b101 =
#280
0"
#285
1!
#287
b1010 I
b1010 D
b100101010000101111111111111110 C
b101 7
b110100011000001111111111111100 9
b100 ;
#290
0!
#295
1"
#297
b11 B
b11111111111111111111111111111110 @
b100101010000101111111111111110 ?
b1010 A
b101010 >
b11001000 =
b110100011000001111111111111100 F
b100 H
#300
0"
#305
1!
#307
b101010 8
b11000110 7
b100101010000101111111111111110 9
b11 ;
0J
b110 I
b110 D
b10100010000110001000000000000 C
#310
0!
#315
1"
#317
b100101010000101111111111111110 F
b11 H
b0 B
b1000000000000 @
b10100010000110001000000000000 ?
b110 A
b101 >
b101010 =
#320
0"
#325
1!
#327
b111 I
b111 D
b101100011000110000000000000001 C
b11010010 7
b10100010000110001000000000000 9
b0 ;
#330
0!
#335
1"
#337
b1 B
b1 @
b101100011000110000000000000001 ?
b111 A
b101 =
b11010010 E
b10100010000110001000000000000 F
b0 H
#340
0"
#345
1!
#347
b100 7
b101100011000110000000000000001 9
b1 ;
b1000 I
b1000 D
b1110100101001010000000000000 C
#350
0!
#355
1"
#357
b100 E
b101100011000110000000000000001 F
b1 H
b0 B
b11111111111111111010000000000000 @
b1110100101001010000000000000 ?
b1000 A
b10100 >
b10100 =
#360
0"
#365
1!
#367
b1001 I
b1001 D
b110100011000001111111111111100 C
b10100 7
b1110100101001010000000000000 9
b0 ;
#370
0!
#375
b0 >
1"
#377
b100 B
b11111111111111111111111111111100 @
b110100011000001111111111111100 ?
b1001 A
b100 =
b10100 E
b1110100101001010000000000000 F
b0 H
#380
0"
#385
1!
#387
b101 7
b110100011000001111111111111100 9
b100 ;
b1010 I
b1010 D
b100101010000101111111111111110 C
#390
0!
#395
1"
#397
b110100011000001111111111111100 F
b100 H
b11 B
b11111111111111111111111111111110 @
b100101010000101111111111111110 ?
b1010 A
b11010010 >
b11001000 =
#400
0"
#405
1!
#407
1J
b110 I
b110 D
b10100010000110001000000000000 C
b11010010 8
b11000110 7
b100101010000101111111111111110 9
b11 ;
#410
0!
#415
1"
#417
b0 B
b1000000000000 @
b10100010000110001000000000000 ?
b110 A
b100 >
b11010010 =
b100101010000101111111111111110 F
b11 H
#420
0"
#425
1!
#427
b1101001000 7
0J
b10100010000110001000000000000 9
b0 ;
b111 I
b111 D
b101100011000110000000000000001 C
#430
0!
#435
1"
#437
b1101001000 E
b10100010000110001000000000000 F
b0 H
b1 B
b1 @
b101100011000110000000000000001 ?
b111 A
b100 =
#440
0"
#445
1!
#447
b1000 I
b1000 D
b1110100101001010000000000000 C
b11 7
b101100011000110000000000000001 9
b1 ;
#450
0!
#455
1"
#457
b0 B
b11111111111111111010000000000000 @
b1110100101001010000000000000 ?
b1000 A
b10100 >
b10100 =
b11 E
b101100011000110000000000000001 F
b1 H
#460
0"
#465
1!
#467
b10100 7
b1110100101001010000000000000 9
b0 ;
b1001 I
b1001 D
b110100011000001111111111111100 C
#470
0!
#475
b0 >
1"
#477
b10100 E
b1110100101001010000000000000 F
b0 H
b100 B
b11111111111111111111111111111100 @
b110100011000001111111111111100 ?
b1001 A
b11 =
#480
0"
#485
1!
#487
b1010 I
b1010 D
b100101010000101111111111111110 C
b101 7
b110100011000001111111111111100 9
b100 ;
#490
0!
#495
1"
#497
b11 B
b11111111111111111111111111111110 @
b100101010000101111111111111110 ?
b1010 A
b1101001000 >
b11001000 =
b110100011000001111111111111100 F
b100 H
#500
0"
#505
1!
#507
b1101001000 8
b11000110 7
b100101010000101111111111111110 9
b11 ;
0J
b110 I
b110 D
b10100010000110001000000000000 C
#510
0!
#515
1"
#517
b100101010000101111111111111110 F
b11 H
b0 B
b1000000000000 @
b10100010000110001000000000000 ?
b110 A
b11 >
b1101001000 =
#520
0"
#525
1!
#527
b111 I
b111 D
b101100011000110000000000000001 C
b100111011000 7
b10100010000110001000000000000 9
b0 ;
#530
0!
#535
1"
#537
b1 B
b1 @
b101100011000110000000000000001 ?
b111 A
b11 =
b100111011000 E
b10100010000110001000000000000 F
b0 H
#540
0"
#545
1!
#547
b10 7
b101100011000110000000000000001 9
b1 ;
b1000 I
b1000 D
b1110100101001010000000000000 C
#550
0!
#555
1"
#557
b10 E
b101100011000110000000000000001 F
b1 H
b0 B
b11111111111111111010000000000000 @
b1110100101001010000000000000 ?
b1000 A
b10100 >
b10100 =
#560
0"
#565
1!
#567
b1001 I
b1001 D
b110100011000001111111111111100 C
b10100 7
b1110100101001010000000000000 9
b0 ;
#570
0!
#575
b0 >
1"
#577
b100 B
b11111111111111111111111111111100 @
b110100011000001111111111111100 ?
b1001 A
b10 =
b10100 E
b1110100101001010000000000000 F
b0 H
#580
0"
#585
1!
#587
b101 7
b110100011000001111111111111100 9
b100 ;
b1010 I
b1010 D
b100101010000101111111111111110 C
#590
0!
#595
1"
#597
b110100011000001111111111111100 F
b100 H
b11 B
b11111111111111111111111111111110 @
b100101010000101111111111111110 ?
b1010 A
b100111011000 >
b11001000 =
#600
0"
#605
1!
#607
1J
b110 I
b110 D
b10100010000110001000000000000 C
b100111011000 8
b11000110 7
b100101010000101111111111111110 9
b11 ;
#610
0!
#615
1"
#617
b0 B
b1000000000000 @
b10100010000110001000000000000 ?
b110 A
b10 >
b100111011000 =
b100101010000101111111111111110 F
b11 H
#620
0"
#625
1!
#627
b1001110110000 7
0J
b10100010000110001000000000000 9
b0 ;
b111 I
b111 D
b101100011000110000000000000001 C
#630
0!
#635
1"
#637
b1001110110000 E
b10100010000110001000000000000 F
b0 H
b1 B
b1 @
b101100011000110000000000000001 ?
b111 A
b10 =
#640
0"
#645
1!
#647
b1000 I
b1000 D
b1110100101001010000000000000 C
b1 7
b101100011000110000000000000001 9
b1 ;
#650
0!
#655
1"
#657
b0 B
b11111111111111111010000000000000 @
b1110100101001010000000000000 ?
b1000 A
b10100 >
b10100 =
b1 E
b101100011000110000000000000001 F
b1 H
#660
0"
#665
1!
#667
b10100 7
b1110100101001010000000000000 9
b0 ;
b1001 I
b1001 D
b110100011000001111111111111100 C
#670
0!
#675
b0 >
1"
#677
b10100 E
b1110100101001010000000000000 F
b0 H
b100 B
b11111111111111111111111111111100 @
b110100011000001111111111111100 ?
b1001 A
b1 =
#680
0"
#685
1!
#687
b1010 I
b1010 D
b100101010000101111111111111110 C
b101 7
b110100011000001111111111111100 9
b100 ;
#690
0!
#695
1"
#697
b11 B
b11111111111111111111111111111110 @
b100101010000101111111111111110 ?
b1010 A
b1001110110000 >
b11001000 =
b110100011000001111111111111100 F
b100 H
#700
0"
#705
1!
#707
b1001110110000 8
b11000110 7
b100101010000101111111111111110 9
b11 ;
0J
b110 I
b110 D
b10100010000110001000000000000 C
#710
0!
#715
1"
#717
b100101010000101111111111111110 F
b11 H
b0 B
b1000000000000 @
b10100010000110001000000000000 ?
b110 A
b1 >
b1001110110000 =
#720
0"
#725
1!
#727
b111 I
b111 D
b101100011000110000000000000001 C
b1001110110000 7
b10100010000110001000000000000 9
b0 ;
#730
0!
#735
1"
#737
b1 B
b1 @
b101100011000110000000000000001 ?
b111 A
b1 =
b1001110110000 E
b10100010000110001000000000000 F
b0 H
#740
0"
#745
1!
#747
b0 7
b101100011000110000000000000001 9
b1 ;
b1000 I
b1000 D
b1110100101001010000000000000 C
#750
0!
#755
1"
#757
b0 E
b101100011000110000000000000001 F
b1 H
b0 B
b11111111111111111010000000000000 @
b1110100101001010000000000000 ?
b1000 A
b10100 >
b10100 =
#760
0"
#765
1!
#767
b1001 I
b1001 D
b110100011000001111111111111100 C
b10100 7
b1110100101001010000000000000 9
b0 ;
#770
0!
#775
b0 >
1"
#777
b100 B
b11111111111111111111111111111100 @
b110100011000001111111111111100 ?
b1001 A
b0 =
b10100 E
b1110100101001010000000000000 F
b0 H
#780
0"
#785
1!
#787
1:
b101 7
b110100011000001111111111111100 9
b100 ;
b1010 I
b1010 D
b100101010000101111111111111110 C
#790
0!
#795
1"
#797
b110100011000001111111111111100 F
b100 H
b11 B
b11111111111111111111111111111110 @
b100101010000101111111111111110 ?
b1010 A
b1001110110000 >
b11001000 =
#800
0"
#805
1!
#807
b1011 I
b1011 D
b11111100000000000000000000000000 C
b11000110 7
b100101010000101111111111111110 9
b11 ;
#810
0!
#815
b0 >
b0 =
1"
#817
b101 B
b0 @
b11111100000000000000000000000000 ?
b1011 A
b100101010000101111111111111110 F
b11 H
#820
0"
#825
1!
#827
b11111100000000000000000000000000 9
b101 ;
b1100 I
b1100 D
bx C
#830
0!
#835
1"
#837
b11111100000000000000000000000000 F
b101 H
bx @
bx ?
b1100 A
bx >
bx =
#840
0"
#845
1!
#847
b1101 I
b1101 D
bx 9
1<
